examples/__init__.py
examples/ai_fuzzer/__init__.py
examples/ai_fuzzer/fuzz_testing_and_model_enhense.py
examples/ai_fuzzer/lenet5_mnist_coverage.py
examples/ai_fuzzer/lenet5_mnist_fuzzing.py
examples/common/__init__.py
examples/common/dataset/__init__.py
examples/common/dataset/data_processing.py
examples/common/networks/__init__.py
examples/common/networks/lenet5/__init__.py
examples/common/networks/lenet5/lenet5_net.py
examples/common/networks/lenet5/lenet5_net_for_fuzzing.py
examples/common/networks/lenet5/mnist_train.py
examples/common/networks/resnet/__init__.py
examples/common/networks/resnet/resnet.py
examples/common/networks/vgg/__init__.py
examples/common/networks/vgg/config.py
examples/common/networks/vgg/crossentropy.py
examples/common/networks/vgg/linear_warmup.py
examples/common/networks/vgg/vgg.py
examples/common/networks/vgg/warmup_cosine_annealing_lr.py
examples/common/networks/vgg/warmup_step_lr.py
examples/common/networks/vgg/utils/__init__.py
examples/common/networks/vgg/utils/util.py
examples/common/networks/vgg/utils/var_init.py
examples/community/__init__.py
examples/model_security/__init__.py
examples/model_security/model_attacks/__init__.py
examples/model_security/model_attacks/black_box/__init__.py
examples/model_security/model_attacks/black_box/mnist_attack_genetic.py
examples/model_security/model_attacks/black_box/mnist_attack_hsja.py
examples/model_security/model_attacks/black_box/mnist_attack_nes.py
examples/model_security/model_attacks/black_box/mnist_attack_pointwise.py
examples/model_security/model_attacks/black_box/mnist_attack_pso.py
examples/model_security/model_attacks/black_box/mnist_attack_salt_and_pepper.py
examples/model_security/model_attacks/white_box/__init__.py
examples/model_security/model_attacks/white_box/mnist_attack_cw.py
examples/model_security/model_attacks/white_box/mnist_attack_deepfool.py
examples/model_security/model_attacks/white_box/mnist_attack_fgsm.py
mindarmour-2.0.0.dist-info/LICENSE
mindarmour-2.0.0.dist-info/METADATA
mindarmour-2.0.0.dist-info/NOTICE
mindarmour-2.0.0.dist-info/WHEEL
mindarmour-2.0.0.dist-info/top_level.txt
mindarmour-2.0.0.dist-info/RECORD
